test
ttbot
