Metadata-Version: 1.0
Name: twisted-telegram-bot
Version: 2.1.2
Summary: Asynchronous Twisted-based Telegram Bot API for Python
Home-page: https://github.com/unintended/twisted-telegram-bot
Author: unintended
Author-email: unintended.github@gmail.com
License: MIT
Platform: UNKNOWN
